pysyslogclient/__init__.py
pysyslogclient/cli.py
syslog-py-server/__init__.py
syslog_py-0.2.5.dist-info/LICENSE
syslog_py-0.2.5.dist-info/METADATA
syslog_py-0.2.5.dist-info/WHEEL
syslog_py-0.2.5.dist-info/top_level.txt
syslog_py-0.2.5.dist-info/RECORD
