Metadata-Version: 2.1
Name: syslog-py
Version: 0.2.5
Summary: Syslog client implementation (RFC 3164/RFC 5424) with message transfer from RFC 6587 (Syslog over TCP)
Home-page: https://github.com/maciejbudzyn/syslog-py
Author: Maciej Budzyński
Author-email: maciej.budzyn@gmail.com
License: UNKNOWN
Keywords: syslog logging octet-counting octet-stuffing
Platform: UNKNOWN
Classifier: Development Status :: 4 - Beta
Classifier: Programming Language :: Python :: 3
Classifier: Operating System :: Unix
Classifier: Operating System :: POSIX :: Linux
Classifier: Operating System :: Microsoft
Requires-Python: >=3.5
